willpyre/__init__.py
willpyre/__main__.py
willpyre/app.py
willpyre/asgi.py
willpyre/common.py
willpyre/kua.py
willpyre/openapi.py
willpyre/router.py
willpyre/schema.py
willpyre/structure.py
willpyre-0.0.18.dist-info/LICENSE
willpyre-0.0.18.dist-info/WHEEL
willpyre-0.0.18.dist-info/METADATA
willpyre-0.0.18.dist-info/RECORD
