Metadata-Version: 2.1
Name: willpyre
Version: 0.0.18
Summary: Willpyre. Fasten your seatbelts!
Author: Nafi Amaan Hossain
Classifier: License :: OSI Approved :: MIT License
Classifier: Programming Language :: Python :: 3.7
Classifier: Programming Language :: Python :: 3.8
Classifier: Programming Language :: Python :: 3.9
Classifier: Programming Language :: Python :: 3.10
